keycode/__init__.py
keycode/__main__.py
keycode/cli.py
keycode/otp.py
keycode/py.typed
keycode/storage.py
keycode-0.1.0.dist-info/METADATA
keycode-0.1.0.dist-info/WHEEL
keycode-0.1.0.dist-info/entry_points.txt
keycode-0.1.0.dist-info/RECORD
