Metadata-Version: 2.4
Name: keycode
Version: 0.1.0
Summary: Add your description here
Author-email: Tanaka Kahwai <tanaka.kahwai@telco.co.zw>
Requires-Python: >=3.12
Requires-Dist: keyring>=25.2.1
Requires-Dist: pyotp>=2.9.0
Requires-Dist: qrcode>=8.2
Requires-Dist: typer>=0.12.3
